algoritmia/__init__.py
algoritmia/utils.py
algoritmia/_examples/__init__.py
algoritmia/_examples/backtracking/__init__.py
algoritmia/_examples/backtracking/coin_change_bt.py
algoritmia/_examples/backtracking/hamiltonian_cycle_bt.py
algoritmia/_examples/backtracking/knapsack_bt.py
algoritmia/_examples/backtracking/nqueens_bt.py
algoritmia/_examples/backtracking/subset_sum_bt.py
algoritmia/_examples/branch_and_bound/__init__.py
algoritmia/_examples/branch_and_bound/coin_change_bab.py
algoritmia/_examples/branch_and_bound/hamiltonian_cycle_bab.py
algoritmia/_examples/branch_and_bound/knapsack_bab.py
algoritmia/_examples/branch_and_bound/subset_sum_bab.py
algoritmia/_examples/divide_and_conquer/__init__.py
algoritmia/_examples/divide_and_conquer/binarysearch.py
algoritmia/_examples/divide_and_conquer/binarysearch_scheme.py
algoritmia/_examples/divide_and_conquer/convex_min.py
algoritmia/_examples/divide_and_conquer/mergesort.py
algoritmia/_examples/divide_and_conquer/mergesort_scheme.py
algoritmia/_examples/divide_and_conquer/power.py
algoritmia/_examples/divide_and_conquer/quicksort.py
algoritmia/_examples/dynamic_programming/__init__.py
algoritmia/_examples/dynamic_programming/coin_change_dp.py
algoritmia/_examples/dynamic_programming/edit_distance.py
algoritmia/_examples/dynamic_programming/gen_coin_change_dp.py
algoritmia/_examples/dynamic_programming/knapsack_dp.py
algoritmia/_examples/graphs/__init__.py
algoritmia/_examples/graphs/find_treasure_labyrinth.py
algoritmia/_examples/graphs/sample_graph.py
algoritmia/_examples/graphs/sample_weighted_graph.py
algoritmia/_examples/greedy/__init__.py
algoritmia/_examples/greedy/activities_selector_greedy.py
algoritmia/_examples/greedy/coin_change_greedy.py
algoritmia/_examples/greedy/frac_knapsack_greedy.py
algoritmia/_examples/greedy/graph_coloring_greedy.py
algoritmia/algorithms/__init__.py
algoritmia/algorithms/connected_components.py
algoritmia/algorithms/license.txt
algoritmia/algorithms/mst.py
algoritmia-4.0.6.dist-info/licenses/LICENSE
algoritmia-4.0.6.dist-info/METADATA
algoritmia-4.0.6.dist-info/WHEEL
algoritmia-4.0.6.dist-info/top_level.txt
algoritmia-4.0.6.dist-info/RECORD
