Metadata-Version: 2.4
Name: algoritmia
Version: 4.0.6
Summary: A library of algorithms and data structures. Used in course EI1022/MT122 (Universitat Jaume I de Castelló)
Author: David Llorens - Andrés Marzal
Maintainer-email: David Llorens <dllorens@uji.es>
License: GNU Affero General Public License v3
Project-URL: homepage, https://github.com/DavidLlorens/algoritmia
Project-URL: changelog, https://github.com/DavidLlorens/algoritmia/blob/main/CHANGELOG.md
Project-URL: Source, https://github.com/DavidLlorens/algoritmia
Keywords: data structures,greedy,divide and conquer,dynamic programming,branch and bound
Classifier: Programming Language :: Python :: 3
Classifier: Operating System :: OS Independent
Requires-Python: >=3.12
License-File: LICENSE
Requires-Dist: easypaint<2,>=1.0.7
Dynamic: license-file
